Workbook

Sheet README
A1: Commonwealth Bank Social Media Dataset
A2: Purpose
A3: This simulated dataset supports Task 3 of the Commonwealth Bank data science program. It mirrors the type of social media content and engagement information learners could analyze without requiring access to a live X/Twitter account.
A4: Important note
A5: All posts and metrics in this workbook are fictional and created for educational use. They should not be treated as real Commonwealth Bank posts, real customer comments, or real performance data.
A6: How learners can use it
A7: Use the Social_Media_Posts sheet to explore sentiment, engagement, customer pain points, recurring topics, and trends over time. The Data_Dictionary sheet explains each column and how it connects to social media/API concepts.
A8: Suggested analyses
A9: 1. Identify the topics that appear most often. 2. Compare engagement across topics, formats, and post types. 3. Review positive, negative, neutral, and mixed sentiment. 4. Find posts with high views but low engagement. 5. Summarize customer questions, complaints, praise, and feature feedback.

Sheet Social_Media_Posts
A1: post_id | B1: post_datetime | C1: post_type | D1: author_type | E1: author_follower_bucket | F1: post_text | G1: topic | H1: content_format | I1: hashtags | J1: mentions_commbank | K1: sentiment_label | L1: sentiment_score | M1: likes | N1: replies | O1: reposts | P1: quote_posts | Q1: views | R1: link_clicks | S1: total_engagements | T1: engagement_rate | U1: day_of_week | V1: customer_intent | W1: response_needed | X1: api_field_examples | Y1: high_views_low_engage
A2: SM001 | B2: 46127.378 | C2: Original post | D2: CommBank | E2: 50k+ | F2: Scam alert: We will never ask for your NetBank password or one-time code by text message. If a message feels suspicious, stop and check before clicking. | G2: Fraud & scams | H2: Text + image | I2: #ScamAwareness #CyberSafety | J2: No | K2: Neutral | L2: 0.1 | M2: 842 | N2: 96 | O2: 310 | P2: 28 | Q2: 118000 | R2: 4200 | S2: =SUM(M2:P2)+R2 -> 5476 | T2: =IFERROR(S2/Q2,0) -> 0.04640678 | U2: =TEXT(B2,"dddd") -> Wednesday | V2: Educational content | W2: No | X2: text, created_at, public_metrics, entities.hashtags | Y2: =IF(AND(Q2>MEDIAN($Q$2:$Q$61), T2<MEDIAN($T$2:$T$61)),"Yes","No") -> No
A3: SM002 | B3: 46127.404 | C3: Reply | D3: Customer | E3: 0-500 | F3: Thanks for the reminder. Nearly clicked on a fake delivery text yesterday and this made me double-check. | G3: Fraud & scams | H3: Text | J3: Yes | K3: Positive | L3: 0.7 | M3: 18 | N3: 3 | O3: 1 | P3: 0 | Q3: 920 | R3: 0 | S3: =SUM(M3:P3)+R3 -> 22 | T3: =IFERROR(S3/Q3,0) -> 0.023913043 | U3: =TEXT(B3,"dddd") -> Wednesday | V3: Praise | W3: No | X3: text, in_reply_to_user_id, referenced_tweets | Y3: =IF(AND(Q3>MEDIAN($Q$2:$Q$61), T3<MEDIAN($T$2:$T$61)),"Yes","No") -> No
A4: SM003 | B4: 46127.428 | C4: Mention | D4: Customer | E4: 0-500 | F4: @CommBank I received a message saying my card is locked. Is this real? The link looks strange. | G4: Fraud & scams | H4: Text | J4: Yes | K4: Negative | L4: -0.35 | M4: 6 | N4: 9 | O4: 0 | P4: 0 | Q4: 780 | R4: 0 | S4: =SUM(M4:P4)+R4 -> 15 | T4: =IFERROR(S4/Q4,0) -> 0.019230769 | U4: =TEXT(B4,"dddd") -> Wednesday | V4: Scam report | W4: Yes | X4: text, entities.mentions, author_id | Y4: =IF(AND(Q4>MEDIAN($Q$2:$Q$61), T4<MEDIAN($T$2:$T$61)),"Yes","No") -> No
A5: SM004 | B5: 46128.521 | C5: Original post | D5: CommBank | E5: 50k+ | F5: New budget habit: split your weekly spend into essentials, savings and fun money before the weekend starts. | G5: Financial wellbeing | H5: Text + image | I5: #MoneyTips #Budgeting | J5: No | K5: Positive | L5: 0.58 | M5: 620 | N5: 42 | O5: 128 | P5: 12 | Q5: 84200 | R5: 5100 | S5: =SUM(M5:P5)+R5 -> 5902 | T5: =IFERROR(S5/Q5,0) -> 0.070095012 | U5: =TEXT(B5,"dddd") -> Thursday | V5: Educational content | W5: No | X5: text, created_at, public_metrics, media_keys | Y5: =IF(AND(Q5>MEDIAN($Q$2:$Q$61), T5<MEDIAN($T$2:$T$61)),"Yes","No") -> No
A6: SM005 | B6: 46128.544 | C6: Reply | D6: Customer | E6: 501-5k | F6: This is actually useful. Would love a template for tracking weekly spending categories. | G6: Financial wellbeing | H6: Text | J6: Yes | K6: Positive | L6: 0.62 | M6: 25 | N6: 2 | O6: 4 | P6: 0 | Q6: 1300 | R6: 0 | S6: =SUM(M6:P6)+R6 -> 31 | T6: =IFERROR(S6/Q6,0) -> 0.023846154 | U6: =TEXT(B6,"dddd") -> Thursday | V6: Feature feedback | W6: No | X6: text, referenced_tweets, public_metrics | Y6: =IF(AND(Q6>MEDIAN($Q$2:$Q$61), T6<MEDIAN($T$2:$T$61)),"Yes","No") -> No
A7: SM006 | B7: 46129.368 | C7: Mention | D7: Customer | E7: 0-500 | F7: @CommBank app keeps timing out this morning. I need to pay rent before work. | G7: Digital banking | H7: Text | J7: Yes | K7: Negative | L7: -0.82 | M7: 41 | N7: 18 | O7: 7 | P7: 1 | Q7: 4500 | R7: 0 | S7: =SUM(M7:P7)+R7 -> 67 | T7: =IFERROR(S7/Q7,0) -> 0.014888889 | U7: =TEXT(B7,"dddd") -> Friday | V7: Complaint | W7: Yes | X7: text, entities.mentions, created_at | Y7: =IF(AND(Q7>MEDIAN($Q$2:$Q$61), T7<MEDIAN($T$2:$T$61)),"Yes","No") -> No
A8: SM007 | B8: 46129.385 | C8: Reply | D8: CommBank | E8: 50k+ | F8: Sorry for the trouble. Please try closing and reopening the app. If the issue continues, send us a private message so we can help. | G8: Customer support | H8: Text | J8: Yes | K8: Neutral | L8: 0.05 | M8: 12 | N8: 5 | O8: 0 | P8: 0 | Q8: 2100 | R8: 0 | S8: =SUM(M8:P8)+R8 -> 17 | T8: =IFERROR(S8/Q8,0) -> 0.0080952381 | U8: =TEXT(B8,"dddd") -> Friday | V8: Customer support | W8: No | X8: text, referenced_tweets, conversation_id | Y8: =IF(AND(Q8>MEDIAN($Q$2:$Q$61), T8<MEDIAN($T$2:$T$61)),"Yes","No") -> No
A9: SM008 | B9: 46130.74 | C9: Original post | D9: CommBank | E9: 50k+ | F9: Planning a home renovation? Compare quotes, keep a buffer for surprises and avoid transferring deposits until you verify the business. | G9: Financial wellbeing | H9: Link | I9: #HomeBudget #MoneySafety | J9: No | K9: Neutral | L9: 0.22 | M9: 208 | N9: 19 | O9: 42 | P9: 5 | Q9: 61200 | R9: 390 | S9: =SUM(M9:P9)+R9 -> 664 | T9: =IFERROR(S9/Q9,0) -> 0.010849673 | U9: =TEXT(B9,"dddd") -> Saturday | V9: Educational content | W9: No | X9: text, entities.urls, public_metrics | Y9: =IF(AND(Q9>MEDIAN($Q$2:$Q$61), T9<MEDIAN($T$2:$T$61)),"Yes","No") -> Yes
A10: SM009 | B10: 46131.472 | C10: Mention | D10: Business customer | E10: 501-5k | F10: Our small business card payment issue was sorted quickly today. Appreciate the support team calling back. | G10: Business banking | H10: Text | J10: Yes | K10: Positive | L10: 0.74 | M10: 53 | N10: 4 | O10: 8 | P10: 1 | Q10: 3900 | R10: 0 | S10: =SUM(M10:P10)+R10 -> 66 | T10: =IFERROR(S10/Q10,0) -> 0.016923077 | U10: =TEXT(B10,"dddd") -> Sunday | V10: Praise | W10: No | X10: text, author_id, public_metrics | Y10: =IF(AND(Q10>MEDIAN($Q$2:$Q$61), T10<MEDIAN($T$2:$T$61)),"Yes","No") -> No
A11: SM010 | B11: 46132.319 | C11: Original post | D11: CommBank | E11: 50k+ | F11: Scheduled maintenance: some card controls and notifications may be unavailable from 1:00am to 3:00am AEST on Sunday. | G11: Outage/service issue | H11: Text | I11: #ServiceUpdate | J11: No | K11: Neutral | L11: 0 | M11: 315 | N11: 88 | O11: 91 | P11: 19 | Q11: 96500 | R11: 800 | S11: =SUM(M11:P11)+R11 -> 1313 | T11: =IFERROR(S11/Q11,0) -> 0.013606218 | U11: =TEXT(B11,"dddd") -> Monday | V11: News/update | W11: No | X11: text, created_at, public_metrics | Y11: =IF(AND(Q11>MEDIAN($Q$2:$Q$61), T11<MEDIAN($T$2:$T$61)),"Yes","No") -> Yes
A12: SM011 | B12: 46132.342 | C12: Reply | D12: Customer | E12: 0-500 | F12: Thanks for giving the timing clearly. Much better than finding out during checkout. | G12: Outage/service issue | H12: Text | J12: Yes | K12: Positive | L12: 0.5 | M12: 14 | N12: 1 | O12: 2 | P12: 0 | Q12: 840 | R12: 0 | S12: =SUM(M12:P12)+R12 -> 17 | T12: =IFERROR(S12/Q12,0) -> 0.020238095 | U12: =TEXT(B12,"dddd") -> Monday | V12: Praise | W12: No | X12: text, referenced_tweets | Y12: =IF(AND(Q12>MEDIAN($Q$2:$Q$61), T12<MEDIAN($T$2:$T$61)),"Yes","No") -> No
A13: SM012 | B13: 46133.753 | C13: Mention | D13: Customer | E13: 0-500 | F13: My transfer has been pending for hours and I can't find a clear status page. Is there an outage? | G13: Outage/service issue | H13: Text | J13: Yes | K13: Negative | L13: -0.76 | M13: 33 | N13: 22 | O13: 4 | P13: 2 | Q13: 5200 | R13: 0 | S13: =SUM(M13:P13)+R13 -> 61 | T13: =IFERROR(S13/Q13,0) -> 0.011730769 | U13: =TEXT(B13,"dddd") -> Tuesday | V13: Question | W13: Yes | X13: text, entities.mentions, created_at | Y13: =IF(AND(Q13>MEDIAN($Q$2:$Q$61), T13<MEDIAN($T$2:$T$61)),"Yes","No") -> No
A14: SM013 | B14: 46134.417 | C14: Original post | D14: CommBank | E14: 50k+ | F14: Three signs a message may be a scam: urgency, unusual links and requests for codes. Pause before you respond. | G14: Security education | H14: Text + video | I14: #CyberSafety #ScamAwareness | J14: No | K14: Positive | L14: 0.46 | M14: 1100 | N14: 72 | O14: 405 | P14: 31 | Q14: 156000 | R14: 7400 | S14: =SUM(M14:P14)+R14 -> 9008 | T14: =IFERROR(S14/Q14,0) -> 0.05774359 | U14: =TEXT(B14,"dddd") -> Wednesday | V14: Educational content | W14: No | X14: text, attachments.media_keys, entities.hashtags | Y14: =IF(AND(Q14>MEDIAN($Q$2:$Q$61), T14<MEDIAN($T$2:$T$61)),"Yes","No") -> No
A15: SM014 | B15: 46134.433 | C15: Quote post | D15: Scam awareness org | E15: 5k-50k | F15: Good practical reminder from @CommBank. The 'urgent action required' wording is still one of the biggest red flags. | G15: Security education | H15: Text | I15: #ScamAwareness | J15: Yes | K15: Positive | L15: 0.67 | M15: 96 | N15: 6 | O15: 31 | P15: 4 | Q15: 6700 | R15: 0 | S15: =SUM(M15:P15)+R15 -> 137 | T15: =IFERROR(S15/Q15,0) -> 0.020447761 | U15: =TEXT(B15,"dddd") -> Wednesday | V15: Educational content | W15: No | X15: text, referenced_tweets, entities.mentions | Y15: =IF(AND(Q15>MEDIAN($Q$2:$Q$61), T15<MEDIAN($T$2:$T$61)),"Yes","No") -> No
A16: SM015 | B16: 46135.604 | C16: Original post | D16: CommBank | E16: 50k+ | F16: We are supporting local community groups with grants focused on financial confidence and digital skills. | G16: Community | H16: Text + image | I16: #Community #FinancialConfidence | J16: No | K16: Positive | L16: 0.63 | M16: 730 | N16: 51 | O16: 144 | P16: 11 | Q16: 102000 | R16: 2900 | S16: =SUM(M16:P16)+R16 -> 3836 | T16: =IFERROR(S16/Q16,0) -> 0.037607843 | U16: =TEXT(B16,"dddd") -> Thursday | V16: Campaign | W16: No | X16: text, entities.hashtags, public_metrics | Y16: =IF(AND(Q16>MEDIAN($Q$2:$Q$61), T16<MEDIAN($T$2:$T$61)),"Yes","No") -> No
A17: SM016 | B17: 46135.63 | C17: Reply | D17: Community org | E17: 501-5k | F17: Proud to be part of this program. The digital skills sessions have already helped our clients feel safer online. | G17: Community | H17: Text | J17: Yes | K17: Positive | L17: 0.86 | M17: 64 | N17: 3 | O17: 13 | P17: 1 | Q17: 4200 | R17: 0 | S17: =SUM(M17:P17)+R17 -> 81 | T17: =IFERROR(S17/Q17,0) -> 0.019285714 | U17: =TEXT(B17,"dddd") -> Thursday | V17: Praise | W17: No | X17: text, author_id, public_metrics | Y17: =IF(AND(Q17>MEDIAN($Q$2:$Q$61), T17<MEDIAN($T$2:$T$61)),"Yes","No") -> No
A18: SM017 | B18: 46136.347 | C18: Mention | D18: Customer | E18: 0-500 | F18: Branch wait times are rough lately. I just need a replacement card and couldn't get through on chat. | G18: Branch/ATM | H18: Text | J18: Yes | K18: Negative | L18: -0.7 | M18: 28 | N18: 12 | O18: 3 | P18: 1 | Q18: 3100 | R18: 0 | S18: =SUM(M18:P18)+R18 -> 44 | T18: =IFERROR(S18/Q18,0) -> 0.014193548 | U18: =TEXT(B18,"dddd") -> Friday | V18: Complaint | W18: Yes | X18: text, entities.mentions | Y18: =IF(AND(Q18>MEDIAN($Q$2:$Q$61), T18<MEDIAN($T$2:$T$61)),"Yes","No") -> No
A19: SM018 | B19: 46137.674 | C19: Original post | D19: CommBank | E19: 50k+ | F19: Travel tip: tell us before you go overseas and check card controls in the app before your first purchase. | G19: Card services | H19: Link | I19: #TravelMoney | J19: No | K19: Neutral | L19: 0.24 | M19: 260 | N19: 34 | O19: 49 | P19: 7 | Q19: 74400 | R19: 1650 | S19: =SUM(M19:P19)+R19 -> 2000 | T19: =IFERROR(S19/Q19,0) -> 0.02688172 | U19: =TEXT(B19,"dddd") -> Saturday | V19: Educational content | W19: No | X19: text, entities.urls, public_metrics | Y19: =IF(AND(Q19>MEDIAN($Q$2:$Q$61), T19<MEDIAN($T$2:$T$61)),"Yes","No") -> No
A20: SM019 | B20: 46137.724 | C20: Reply | D20: Customer | E20: 0-500 | F20: Can I still use Apple Pay if my physical card is blocked while travelling? | G20: Card services | H20: Text | J20: Yes | K20: Neutral | L20: 0.05 | M20: 9 | N20: 4 | O20: 1 | P20: 0 | Q20: 1050 | R20: 0 | S20: =SUM(M20:P20)+R20 -> 14 | T20: =IFERROR(S20/Q20,0) -> 0.013333333 | U20: =TEXT(B20,"dddd") -> Saturday | V20: Question | W20: Yes | X20: text, referenced_tweets | Y20: =IF(AND(Q20>MEDIAN($Q$2:$Q$61), T20<MEDIAN($T$2:$T$61)),"Yes","No") -> No
A21: SM020 | B21: 46138.375 | C21: Original post | D21: CommBank | E21: 50k+ | F21: Small business owners: join our free webinar on cash flow planning and preparing for quieter trading periods. | G21: Business banking | H21: Link | I21: #SmallBusiness #CashFlow | J21: No | K21: Positive | L21: 0.48 | M21: 188 | N21: 17 | O21: 66 | P21: 3 | Q21: 54300 | R21: 2300 | S21: =SUM(M21:P21)+R21 -> 2574 | T21: =IFERROR(S21/Q21,0) -> 0.047403315 | U21: =TEXT(B21,"dddd") -> Sunday | V21: Campaign | W21: No | X21: text, entities.urls, public_metrics | Y21: =IF(AND(Q21>MEDIAN($Q$2:$Q$61), T21<MEDIAN($T$2:$T$61)),"Yes","No") -> No
A22: SM021 | B22: 46139.33 | C22: Mention | D22: Business customer | E22: 501-5k | F22: Would love more examples for seasonal businesses in the cash flow webinar. Retail is not the same as consulting. | G22: Business banking | H22: Text | I22: #SmallBusiness | J22: Yes | K22: Mixed | L22: 0.12 | M22: 22 | N22: 5 | O22: 4 | P22: 0 | Q22: 1700 | R22: 0 | S22: =SUM(M22:P22)+R22 -> 31 | T22: =IFERROR(S22/Q22,0) -> 0.018235294 | U22: =TEXT(B22,"dddd") -> Monday | V22: Feature feedback | W22: No | X22: text, entities.hashtags, entities.mentions | Y22: =IF(AND(Q22>MEDIAN($Q$2:$Q$61), T22<MEDIAN($T$2:$T$61)),"Yes","No") -> No
A23: SM022 | B23: 46140.51 | C23: Original post | D23: CommBank | E23: 50k+ | F23: We have added clearer transaction labels in the app to help you recognise subscriptions and recurring payments. | G23: Digital banking | H23: Text + image | I23: #CommBankApp | J23: No | K23: Positive | L23: 0.55 | M23: 980 | N23: 104 | O23: 218 | P23: 26 | Q23: 142500 | R23: 6100 | S23: =SUM(M23:P23)+R23 -> 7428 | T23: =IFERROR(S23/Q23,0) -> 0.052126316 | U23: =TEXT(B23,"dddd") -> Tuesday | V23: Product update | W23: No | X23: text, public_metrics, attachments.media_keys | Y23: =IF(AND(Q23>MEDIAN($Q$2:$Q$61), T23<MEDIAN($T$2:$T$61)),"Yes","No") -> No
A24: SM023 | B24: 46140.533 | C24: Reply | D24: Customer | E24: 0-500 | F24: Finally! I have been trying to work out what one of my monthly charges was for ages. | G24: Digital banking | H24: Text | J24: Yes | K24: Positive | L24: 0.64 | M24: 31 | N24: 2 | O24: 3 | P24: 0 | Q24: 1800 | R24: 0 | S24: =SUM(M24:P24)+R24 -> 36 | T24: =IFERROR(S24/Q24,0) -> 0.02 | U24: =TEXT(B24,"dddd") -> Tuesday | V24: Praise | W24: No | X24: text, referenced_tweets | Y24: =IF(AND(Q24>MEDIAN($Q$2:$Q$61), T24<MEDIAN($T$2:$T$61)),"Yes","No") -> No
A25: SM024 | B25: 46140.545 | C25: Reply | D25: Customer | E25: 0-500 | F25: Please add a way to rename merchants manually too. Some labels are still confusing. | G25: Digital banking | H25: Text | J25: Yes | K25: Mixed | L25: 0.08 | M25: 44 | N25: 7 | O25: 5 | P25: 1 | Q25: 2600 | R25: 0 | S25: =SUM(M25:P25)+R25 -> 57 | T25: =IFERROR(S25/Q25,0) -> 0.021923077 | U25: =TEXT(B25,"dddd") -> Tuesday | V25: Feature feedback | W25: No | X25: text, referenced_tweets, public_metrics | Y25: =IF(AND(Q25>MEDIAN($Q$2:$Q$61), T25<MEDIAN($T$2:$T$61)),"Yes","No") -> No
A26: SM025 | B26: 46141.812 | C26: Mention | D26: Customer | E26: 0-500 | F26: ATM near my station has been out of service twice this week. Any update? | G26: Branch/ATM | H26: Text | J26: Yes | K26: Negative | L26: -0.58 | M26: 12 | N26: 8 | O26: 1 | P26: 0 | Q26: 1400 | R26: 0 | S26: =SUM(M26:P26)+R26 -> 21 | T26: =IFERROR(S26/Q26,0) -> 0.015 | U26: =TEXT(B26,"dddd") -> Wednesday | V26: Question | W26: Yes | X26: text, entities.mentions, created_at | Y26: =IF(AND(Q26>MEDIAN($Q$2:$Q$61), T26<MEDIAN($T$2:$T$61)),"Yes","No") -> No
A27: SM026 | B27: 46143.378 | C27: Original post | D27: CommBank | E27: 50k+ | F27: Start the month by checking subscriptions you no longer use. Small recurring payments can add up quickly. | G27: Financial wellbeing | H27: Text + image | I27: #MoneyTips | J27: No | K27: Positive | L27: 0.51 | M27: 760 | N27: 38 | O27: 160 | P27: 13 | Q27: 100400 | R27: 4800 | S27: =SUM(M27:P27)+R27 -> 5771 | T27: =IFERROR(S27/Q27,0) -> 0.05748008 | U27: =TEXT(B27,"dddd") -> Friday | V27: Educational content | W27: No | X27: text, created_at, public_metrics | Y27: =IF(AND(Q27>MEDIAN($Q$2:$Q$61), T27<MEDIAN($T$2:$T$61)),"Yes","No") -> No
A28: SM027 | B28: 46144.425 | C28: Mention | D28: Customer | E28: 501-5k | F28: The new transaction labels are helpful, but my rent payment is now showing as entertainment, which is... optimistic. | G28: Digital banking | H28: Text | J28: Yes | K28: Mixed | L28: -0.05 | M28: 105 | N28: 11 | O28: 14 | P28: 2 | Q28: 9800 | R28: 0 | S28: =SUM(M28:P28)+R28 -> 132 | T28: =IFERROR(S28/Q28,0) -> 0.013469388 | U28: =TEXT(B28,"dddd") -> Saturday | V28: Feature feedback | W28: No | X28: text, entities.mentions | Y28: =IF(AND(Q28>MEDIAN($Q$2:$Q$61), T28<MEDIAN($T$2:$T$61)),"Yes","No") -> Yes
A29: SM028 | B29: 46145.556 | C29: Original post | D29: CommBank | E29: 50k+ | F29: If you are buying online, use secure payment options and be cautious of sellers asking to move the conversation off-platform. | G29: Fraud & scams | H29: Text + video | I29: #OnlineSafety #ScamAwareness | J29: No | K29: Neutral | L29: 0.2 | M29: 520 | N29: 44 | O29: 205 | P29: 15 | Q29: 132000 | R29: 6900 | S29: =SUM(M29:P29)+R29 -> 7684 | T29: =IFERROR(S29/Q29,0) -> 0.058212121 | U29: =TEXT(B29,"dddd") -> Sunday | V29: Educational content | W29: No | X29: text, attachments.media_keys, entities.hashtags | Y29: =IF(AND(Q29>MEDIAN($Q$2:$Q$61), T29<MEDIAN($T$2:$T$61)),"Yes","No") -> No
A30: SM029 | B30: 46145.589 | C30: Reply | D30: Customer | E30: 0-500 | F30: This happened to me on a marketplace sale. A checklist would be really helpful. | G30: Fraud & scams | H30: Text | J30: Yes | K30: Mixed | L30: -0.1 | M30: 21 | N30: 3 | O30: 2 | P30: 0 | Q30: 1150 | R30: 0 | S30: =SUM(M30:P30)+R30 -> 26 | T30: =IFERROR(S30/Q30,0) -> 0.022608696 | U30: =TEXT(B30,"dddd") -> Sunday | V30: Feature feedback | W30: No | X30: text, referenced_tweets | Y30: =IF(AND(Q30>MEDIAN($Q$2:$Q$61), T30<MEDIAN($T$2:$T$61)),"Yes","No") -> No
A31: SM030 | B31: 46146.365 | C31: Mention | D31: Customer | E31: 0-500 | F31: Locked out of NetBank after changing phones. The recovery steps are not clear. | G31: Digital banking | H31: Text | J31: Yes | K31: Negative | L31: -0.69 | M31: 39 | N31: 15 | O31: 4 | P31: 1 | Q31: 4300 | R31: 0 | S31: =SUM(M31:P31)+R31 -> 59 | T31: =IFERROR(S31/Q31,0) -> 0.01372093 | U31: =TEXT(B31,"dddd") -> Monday | V31: Complaint | W31: Yes | X31: text, entities.mentions | Y31: =IF(AND(Q31>MEDIAN($Q$2:$Q$61), T31<MEDIAN($T$2:$T$61)),"Yes","No") -> No
A32: SM031 | B32: 46147.458 | C32: Original post | D32: CommBank | E32: 50k+ | F32: Today we are sharing practical tips for protecting older family members from impersonation scams. | G32: Fraud & scams | H32: Link | I32: #ScamAwareness #FamilySafety | J32: No | K32: Positive | L32: 0.42 | M32: 900 | N32: 82 | O32: 360 | P32: 33 | Q32: 170000 | R32: 8900 | S32: =SUM(M32:P32)+R32 -> 10275 | T32: =IFERROR(S32/Q32,0) -> 0.060441176 | U32: =TEXT(B32,"dddd") -> Tuesday | V32: Educational content | W32: No | X32: text, entities.urls, public_metrics | Y32: =IF(AND(Q32>MEDIAN($Q$2:$Q$61), T32<MEDIAN($T$2:$T$61)),"Yes","No") -> No
A33: SM032 | B33: 46147.501 | C33: Quote post | D33: News/media | E33: 50k+ | F33: Useful consumer safety advice from @CommBank as impersonation scams continue to target older Australians. | G33: Fraud & scams | H33: Text | I33: #ScamAwareness | J33: Yes | K33: Positive | L33: 0.45 | M33: 230 | N33: 18 | O33: 71 | P33: 9 | Q33: 31000 | R33: 0 | S33: =SUM(M33:P33)+R33 -> 328 | T33: =IFERROR(S33/Q33,0) -> 0.010580645 | U33: =TEXT(B33,"dddd") -> Tuesday | V33: News/update | W33: No | X33: text, referenced_tweets, public_metrics | Y33: =IF(AND(Q33>MEDIAN($Q$2:$Q$61), T33<MEDIAN($T$2:$T$61)),"Yes","No") -> Yes
A34: SM033 | B34: 46148.691 | C34: Original post | D34: CommBank | E34: 50k+ | F34: We are trialling new in-app prompts that ask customers to pause before sending money to a first-time payee. | G34: Security education | H34: Text + image | I34: #CyberSafety | J34: No | K34: Positive | L34: 0.4 | M34: 480 | N34: 93 | O34: 156 | P34: 24 | Q34: 124000 | R34: 4100 | S34: =SUM(M34:P34)+R34 -> 4853 | T34: =IFERROR(S34/Q34,0) -> 0.039137097 | U34: =TEXT(B34,"dddd") -> Wednesday | V34: Product update | W34: No | X34: text, public_metrics, attachments.media_keys | Y34: =IF(AND(Q34>MEDIAN($Q$2:$Q$61), T34<MEDIAN($T$2:$T$61)),"Yes","No") -> No
A35: SM034 | B35: 46148.716 | C35: Reply | D35: Customer | E35: 0-500 | F35: Good idea, but please make sure it does not slow down urgent transfers to family. | G35: Security education | H35: Text | J35: Yes | K35: Mixed | L35: 0.04 | M35: 34 | N35: 6 | O35: 2 | P35: 0 | Q35: 2100 | R35: 0 | S35: =SUM(M35:P35)+R35 -> 42 | T35: =IFERROR(S35/Q35,0) -> 0.02 | U35: =TEXT(B35,"dddd") -> Wednesday | V35: Feature feedback | W35: No | X35: text, referenced_tweets | Y35: =IF(AND(Q35>MEDIAN($Q$2:$Q$61), T35<MEDIAN($T$2:$T$61)),"Yes","No") -> No
A36: SM035 | B36: 46149.312 | C36: Mention | D36: Customer | E36: 0-500 | F36: Is PayID down? Two people have tried to pay me and both transfers are stuck. | G36: Outage/service issue | H36: Text | I36: #PayID | J36: Yes | K36: Negative | L36: -0.74 | M36: 52 | N36: 21 | O36: 8 | P36: 3 | Q36: 7700 | R36: 0 | S36: =SUM(M36:P36)+R36 -> 84 | T36: =IFERROR(S36/Q36,0) -> 0.010909091 | U36: =TEXT(B36,"dddd") -> Thursday | V36: Question | W36: Yes | X36: text, entities.hashtags, entities.mentions | Y36: =IF(AND(Q36>MEDIAN($Q$2:$Q$61), T36<MEDIAN($T$2:$T$61)),"Yes","No") -> Yes
A37: SM036 | B37: 46149.335 | C37: Reply | D37: CommBank | E37: 50k+ | F37: We are aware some customers are seeing delays with PayID transfers and our teams are investigating. We will share updates as soon as possible. | G37: Outage/service issue | H37: Text | I37: #ServiceUpdate | J37: Yes | K37: Neutral | L37: 0 | M37: 141 | N37: 47 | O37: 39 | P37: 12 | Q37: 21900 | R37: 0 | S37: =SUM(M37:P37)+R37 -> 239 | T37: =IFERROR(S37/Q37,0) -> 0.010913242 | U37: =TEXT(B37,"dddd") -> Thursday | V37: Customer support | W37: No | X37: text, conversation_id, public_metrics | Y37: =IF(AND(Q37>MEDIAN($Q$2:$Q$61), T37<MEDIAN($T$2:$T$61)),"Yes","No") -> Yes
A38: SM037 | B38: 46151.434 | C38: Original post | D38: CommBank | E38: 50k+ | F38: Know the difference between available balance and current balance before making a large purchase. | G38: Financial wellbeing | H38: Text + image | I38: #MoneyTips #BankingBasics | J38: No | K38: Neutral | L38: 0.25 | M38: 390 | N38: 29 | O38: 85 | P38: 4 | Q38: 90300 | R38: 2500 | S38: =SUM(M38:P38)+R38 -> 3008 | T38: =IFERROR(S38/Q38,0) -> 0.033311185 | U38: =TEXT(B38,"dddd") -> Saturday | V38: Educational content | W38: No | X38: text, entities.hashtags, public_metrics | Y38: =IF(AND(Q38>MEDIAN($Q$2:$Q$61), T38<MEDIAN($T$2:$T$61)),"Yes","No") -> No
A39: SM038 | B39: 46152.785 | C39: Mention | D39: Customer | E39: 0-500 | F39: Just used the spend tracker for the first time and it was a wake-up call, in a good way. | G39: Financial wellbeing | H39: Text | J39: Yes | K39: Positive | L39: 0.79 | M39: 47 | N39: 2 | O39: 5 | P39: 0 | Q39: 2500 | R39: 0 | S39: =SUM(M39:P39)+R39 -> 54 | T39: =IFERROR(S39/Q39,0) -> 0.0216 | U39: =TEXT(B39,"dddd") -> Sunday | V39: Praise | W39: No | X39: text, entities.mentions | Y39: =IF(AND(Q39>MEDIAN($Q$2:$Q$61), T39<MEDIAN($T$2:$T$61)),"Yes","No") -> No
A40: SM039 | B40: 46154.385 | C40: Original post | D40: CommBank | E40: 50k+ | F40: Card controls can help if your card is misplaced. Temporarily lock, unlock or replace your card in the app. | G40: Card services | H40: Text + video | I40: #CommBankApp | J40: No | K40: Positive | L40: 0.38 | M40: 670 | N40: 58 | O40: 142 | P40: 16 | Q40: 111000 | R40: 5300 | S40: =SUM(M40:P40)+R40 -> 6186 | T40: =IFERROR(S40/Q40,0) -> 0.05572973 | U40: =TEXT(B40,"dddd") -> Tuesday | V40: Educational content | W40: No | X40: text, attachments.media_keys, public_metrics | Y40: =IF(AND(Q40>MEDIAN($Q$2:$Q$61), T40<MEDIAN($T$2:$T$61)),"Yes","No") -> No
A41: SM040 | B41: 46154.41 | C41: Reply | D41: Customer | E41: 501-5k | F41: This saved me last month. Found the card under my car seat after locking it in the app. | G41: Card services | H41: Text | J41: Yes | K41: Positive | L41: 0.83 | M41: 89 | N41: 5 | O41: 9 | P41: 0 | Q41: 6000 | R41: 0 | S41: =SUM(M41:P41)+R41 -> 103 | T41: =IFERROR(S41/Q41,0) -> 0.017166667 | U41: =TEXT(B41,"dddd") -> Tuesday | V41: Praise | W41: No | X41: text, referenced_tweets | Y41: =IF(AND(Q41>MEDIAN($Q$2:$Q$61), T41<MEDIAN($T$2:$T$61)),"Yes","No") -> No
A42: SM041 | B42: 46156.587 | C42: Original post | D42: CommBank | E42: 50k+ | F42: We are investing in energy efficiency upgrades across selected branches to reduce operational emissions. | G42: Sustainability | H42: Text + image | I42: #Sustainability | J42: No | K42: Positive | L42: 0.32 | M42: 310 | N42: 112 | O42: 74 | P42: 18 | Q42: 98000 | R42: 1200 | S42: =SUM(M42:P42)+R42 -> 1714 | T42: =IFERROR(S42/Q42,0) -> 0.017489796 | U42: =TEXT(B42,"dddd") -> Thursday | V42: News/update | W42: No | X42: text, entities.hashtags, public_metrics | Y42: =IF(AND(Q42>MEDIAN($Q$2:$Q$61), T42<MEDIAN($T$2:$T$61)),"Yes","No") -> Yes
A43: SM042 | B43: 46156.626 | C43: Reply | D43: Customer | E43: 0-500 | F43: Good, but customers also want greener lending options and clearer reporting. | G43: Sustainability | H43: Text | J43: Yes | K43: Mixed | L43: 0.02 | M43: 58 | N43: 8 | O43: 6 | P43: 1 | Q43: 3400 | R43: 0 | S43: =SUM(M43:P43)+R43 -> 73 | T43: =IFERROR(S43/Q43,0) -> 0.021470588 | U43: =TEXT(B43,"dddd") -> Thursday | V43: Feature feedback | W43: No | X43: text, referenced_tweets | Y43: =IF(AND(Q43>MEDIAN($Q$2:$Q$61), T43<MEDIAN($T$2:$T$61)),"Yes","No") -> No
A44: SM043 | B44: 46158.486 | C44: Mention | D44: Customer | E44: 0-500 | F44: The ATM locator sent me to a branch that has moved. Please update the map. | G44: Branch/ATM | H44: Text | J44: Yes | K44: Negative | L44: -0.62 | M44: 17 | N44: 6 | O44: 2 | P44: 0 | Q44: 1250 | R44: 0 | S44: =SUM(M44:P44)+R44 -> 25 | T44: =IFERROR(S44/Q44,0) -> 0.02 | U44: =TEXT(B44,"dddd") -> Saturday | V44: Complaint | W44: Yes | X44: text, entities.mentions | Y44: =IF(AND(Q44>MEDIAN($Q$2:$Q$61), T44<MEDIAN($T$2:$T$61)),"Yes","No") -> No
A45: SM044 | B45: 46160.372 | C45: Original post | D45: CommBank | E45: 50k+ | F45: Before tax time, check that your bank statements and interest summaries are easy to access in NetBank. | G45: Digital banking | H45: Link | I45: #TaxTime #NetBank | J45: No | K45: Neutral | L45: 0.18 | M45: 240 | N45: 26 | O45: 58 | P45: 6 | Q45: 88000 | R45: 2100 | S45: =SUM(M45:P45)+R45 -> 2430 | T45: =IFERROR(S45/Q45,0) -> 0.027613636 | U45: =TEXT(B45,"dddd") -> Monday | V45: Educational content | W45: No | X45: text, entities.urls, public_metrics | Y45: =IF(AND(Q45>MEDIAN($Q$2:$Q$61), T45<MEDIAN($T$2:$T$61)),"Yes","No") -> No
A46: SM045 | B46: 46161.799 | C46: Mention | D46: Customer | E46: 0-500 | F46: Trying to download statements and the page keeps refreshing. Anyone else? | G46: Digital banking | H46: Text | I46: #NetBank | J46: Yes | K46: Negative | L46: -0.57 | M46: 36 | N46: 13 | O46: 5 | P46: 1 | Q46: 4600 | R46: 0 | S46: =SUM(M46:P46)+R46 -> 55 | T46: =IFERROR(S46/Q46,0) -> 0.011956522 | U46: =TEXT(B46,"dddd") -> Tuesday | V46: Question | W46: Yes | X46: text, entities.hashtags, entities.mentions | Y46: =IF(AND(Q46>MEDIAN($Q$2:$Q$61), T46<MEDIAN($T$2:$T$61)),"Yes","No") -> No
A47: SM046 | B47: 46163.542 | C47: Original post | D47: CommBank | E47: 50k+ | F47: Thinking about your first credit card? Compare fees, interest rates and repayment habits before applying. | G47: Financial wellbeing | H47: Link | I47: #BankingBasics #MoneyTips | J47: No | K47: Neutral | L47: 0.2 | M47: 280 | N47: 37 | O47: 69 | P47: 9 | Q47: 79000 | R47: 3400 | S47: =SUM(M47:P47)+R47 -> 3795 | T47: =IFERROR(S47/Q47,0) -> 0.048037975 | U47: =TEXT(B47,"dddd") -> Thursday | V47: Educational content | W47: No | X47: text, entities.urls, public_metrics | Y47: =IF(AND(Q47>MEDIAN($Q$2:$Q$61), T47<MEDIAN($T$2:$T$61)),"Yes","No") -> No
A48: SM047 | B48: 46164.438 | C48: Reply | D48: Customer | E48: 0-500 | F48: Can you make an explainer for students who are new to credit? The language is still intimidating. | G48: Financial wellbeing | H48: Text | J48: Yes | K48: Neutral | L48: 0.11 | M48: 23 | N48: 3 | O48: 3 | P48: 0 | Q48: 1600 | R48: 0 | S48: =SUM(M48:P48)+R48 -> 29 | T48: =IFERROR(S48/Q48,0) -> 0.018125 | U48: =TEXT(B48,"dddd") -> Friday | V48: Feature feedback | W48: No | X48: text, referenced_tweets | Y48: =IF(AND(Q48>MEDIAN($Q$2:$Q$61), T48<MEDIAN($T$2:$T$61)),"Yes","No") -> No
A49: SM048 | B49: 46166.682 | C49: Original post | D49: CommBank | E49: 50k+ | F49: Reminder: genuine bank staff will not ask you to transfer money to a 'safe account'. Stop, check and report suspicious requests. | G49: Fraud & scams | H49: Text + image | I49: #ScamAwareness #StopCheckReport | J49: No | K49: Neutral | L49: 0.16 | M49: 1280 | N49: 118 | O49: 520 | P49: 47 | Q49: 210000 | R49: 10200 | S49: =SUM(M49:P49)+R49 -> 12165 | T49: =IFERROR(S49/Q49,0) -> 0.057928571 | U49: =TEXT(B49,"dddd") -> Sunday | V49: Educational content | W49: No | X49: text, entities.hashtags, public_metrics | Y49: =IF(AND(Q49>MEDIAN($Q$2:$Q$61), T49<MEDIAN($T$2:$T$61)),"Yes","No") -> No
A50: SM049 | B50: 46166.712 | C50: Mention | D50: Customer | E50: 0-500 | F50: A caller used the safe account line on my mum today. She hung up because she'd seen your post. | G50: Fraud & scams | H50: Text | J50: Yes | K50: Positive | L50: 0.66 | M50: 76 | N50: 4 | O50: 13 | P50: 0 | Q50: 5200 | R50: 0 | S50: =SUM(M50:P50)+R50 -> 93 | T50: =IFERROR(S50/Q50,0) -> 0.017884615 | U50: =TEXT(B50,"dddd") -> Sunday | V50: Praise | W50: No | X50: text, entities.mentions | Y50: =IF(AND(Q50>MEDIAN($Q$2:$Q$61), T50<MEDIAN($T$2:$T$61)),"Yes","No") -> No
A51: SM050 | B51: 46169.403 | C51: Original post | D51: CommBank | E51: 50k+ | F51: We are updating the app home screen to make upcoming bills and scheduled payments easier to find. | G51: Digital banking | H51: Text + image | I51: #CommBankApp | J51: No | K51: Positive | L51: 0.44 | M51: 720 | N51: 156 | O51: 132 | P51: 35 | Q51: 149000 | R51: 4800 | S51: =SUM(M51:P51)+R51 -> 5843 | T51: =IFERROR(S51/Q51,0) -> 0.039214765 | U51: =TEXT(B51,"dddd") -> Wednesday | V51: Product update | W51: No | X51: text, public_metrics, attachments.media_keys | Y51: =IF(AND(Q51>MEDIAN($Q$2:$Q$61), T51<MEDIAN($T$2:$T$61)),"Yes","No") -> No
A52: SM051 | B52: 46169.42 | C52: Reply | D52: Customer | E52: 0-500 | F52: Please do not move everything again. The last redesign made regular transfers harder to find. | G52: Digital banking | H52: Text | J52: Yes | K52: Negative | L52: -0.49 | M52: 67 | N52: 12 | O52: 5 | P52: 2 | Q52: 3900 | R52: 0 | S52: =SUM(M52:P52)+R52 -> 86 | T52: =IFERROR(S52/Q52,0) -> 0.022051282 | U52: =TEXT(B52,"dddd") -> Wednesday | V52: Feature feedback | W52: No | X52: text, referenced_tweets | Y52: =IF(AND(Q52>MEDIAN($Q$2:$Q$61), T52<MEDIAN($T$2:$T$61)),"Yes","No") -> No
A53: SM052 | B53: 46170.552 | C53: Mention | D53: Customer | E53: 501-5k | F53: Credit where due: the fraud team called quickly after I reported a suspicious transfer. | G53: Fraud & scams | H53: Text | J53: Yes | K53: Positive | L53: 0.76 | M53: 112 | N53: 6 | O53: 18 | P53: 1 | Q53: 7600 | R53: 0 | S53: =SUM(M53:P53)+R53 -> 137 | T53: =IFERROR(S53/Q53,0) -> 0.018026316 | U53: =TEXT(B53,"dddd") -> Thursday | V53: Praise | W53: No | X53: text, entities.mentions, public_metrics | Y53: =IF(AND(Q53>MEDIAN($Q$2:$Q$61), T53<MEDIAN($T$2:$T$61)),"Yes","No") -> Yes
A54: SM053 | B54: 46174.354 | C54: Original post | D54: CommBank | E54: 50k+ | F54: Winter energy bills can be unpredictable. Build a small buffer where possible and review direct debits before they are due. | G54: Financial wellbeing | H54: Text + image | I54: #MoneyTips #Budgeting | J54: No | K54: Neutral | L54: 0.21 | M54: 340 | N54: 31 | O54: 76 | P54: 8 | Q54: 93000 | R54: 3600 | S54: =SUM(M54:P54)+R54 -> 4055 | T54: =IFERROR(S54/Q54,0) -> 0.043602151 | U54: =TEXT(B54,"dddd") -> Monday | V54: Educational content | W54: No | X54: text, created_at, public_metrics | Y54: =IF(AND(Q54>MEDIAN($Q$2:$Q$61), T54<MEDIAN($T$2:$T$61)),"Yes","No") -> No
A55: SM054 | B55: 46175.764 | C55: Mention | D55: Customer | E55: 0-500 | F55: Can the app notify me before a direct debit if my balance is low? That would prevent a lot of stress. | G55: Digital banking | H55: Text | J55: Yes | K55: Mixed | L55: 0.15 | M55: 84 | N55: 10 | O55: 11 | P55: 1 | Q55: 5900 | R55: 0 | S55: =SUM(M55:P55)+R55 -> 106 | T55: =IFERROR(S55/Q55,0) -> 0.017966102 | U55: =TEXT(B55,"dddd") -> Tuesday | V55: Feature feedback | W55: No | X55: text, entities.mentions | Y55: =IF(AND(Q55>MEDIAN($Q$2:$Q$61), T55<MEDIAN($T$2:$T$61)),"Yes","No") -> No
A56: SM055 | B56: 46178.5 | C56: Original post | D56: CommBank | E56: 50k+ | F56: We are celebrating teams volunteering with local partners to improve financial confidence in regional communities. | G56: Community | H56: Text + video | I56: #Community #Volunteering | J56: No | K56: Positive | L56: 0.69 | M56: 860 | N56: 44 | O56: 188 | P56: 14 | Q56: 125000 | R56: 3100 | S56: =SUM(M56:P56)+R56 -> 4206 | T56: =IFERROR(S56/Q56,0) -> 0.033648 | U56: =TEXT(B56,"dddd") -> Friday | V56: Campaign | W56: No | X56: text, attachments.media_keys, entities.hashtags | Y56: =IF(AND(Q56>MEDIAN($Q$2:$Q$61), T56<MEDIAN($T$2:$T$61)),"Yes","No") -> No
A57: SM056 | B57: 46179.649 | C57: Quote post | D57: Community org | E57: 501-5k | F57: Thank you @CommBank for supporting practical financial education in our region. | G57: Community | H57: Text + image | I57: #Community | J57: Yes | K57: Positive | L57: 0.88 | M57: 122 | N57: 4 | O57: 28 | P57: 2 | Q57: 6900 | R57: 0 | S57: =SUM(M57:P57)+R57 -> 156 | T57: =IFERROR(S57/Q57,0) -> 0.022608696 | U57: =TEXT(B57,"dddd") -> Saturday | V57: Praise | W57: No | X57: text, referenced_tweets, entities.mentions | Y57: =IF(AND(Q57>MEDIAN($Q$2:$Q$61), T57<MEDIAN($T$2:$T$61)),"Yes","No") -> No
A58: SM057 | B58: 46182.392 | C58: Original post | D58: CommBank | E58: 50k+ | F58: If a payment request arrives unexpectedly, call the person on a trusted number before sending money. | G58: Security education | H58: Text + image | I58: #CyberSafety #StopCheckReport | J58: No | K58: Neutral | L58: 0.19 | M58: 740 | N58: 63 | O58: 295 | P58: 22 | Q58: 151000 | R58: 7200 | S58: =SUM(M58:P58)+R58 -> 8320 | T58: =IFERROR(S58/Q58,0) -> 0.055099338 | U58: =TEXT(B58,"dddd") -> Tuesday | V58: Educational content | W58: No | X58: text, entities.hashtags, public_metrics | Y58: =IF(AND(Q58>MEDIAN($Q$2:$Q$61), T58<MEDIAN($T$2:$T$61)),"Yes","No") -> No
A59: SM058 | B59: 46183.842 | C59: Mention | D59: Customer | E59: 0-500 | F59: Why is there no clear scam reporting button in the app? I had to search around for it. | G59: Fraud & scams | H59: Text | J59: Yes | K59: Negative | L59: -0.64 | M59: 45 | N59: 12 | O59: 4 | P59: 1 | Q59: 4100 | R59: 0 | S59: =SUM(M59:P59)+R59 -> 62 | T59: =IFERROR(S59/Q59,0) -> 0.015121951 | U59: =TEXT(B59,"dddd") -> Wednesday | V59: Complaint | W59: Yes | X59: text, entities.mentions | Y59: =IF(AND(Q59>MEDIAN($Q$2:$Q$61), T59<MEDIAN($T$2:$T$61)),"Yes","No") -> No
A60: SM059 | B60: 46185.465 | C60: Original post | D60: CommBank | E60: 50k+ | F60: Our app update includes accessibility improvements for screen readers and clearer error messages. | G60: Digital banking | H60: Text + image | I60: #CommBankApp #Accessibility | J60: No | K60: Positive | L60: 0.61 | M60: 690 | N60: 73 | O60: 148 | P60: 20 | Q60: 121000 | R60: 3900 | S60: =SUM(M60:P60)+R60 -> 4831 | T60: =IFERROR(S60/Q60,0) -> 0.03992562 | U60: =TEXT(B60,"dddd") -> Friday | V60: Product update | W60: No | X60: text, entities.hashtags, public_metrics | Y60: =IF(AND(Q60>MEDIAN($Q$2:$Q$61), T60<MEDIAN($T$2:$T$61)),"Yes","No") -> No
A61: SM060 | B61: 46185.504 | C61: Reply | D61: Customer | E61: 0-500 | F61: The clearer error messages help. Please make the font size easier to adjust too. | G61: Digital banking | H61: Text | J61: Yes | K61: Mixed | L61: 0.25 | M61: 38 | N61: 5 | O61: 3 | P61: 0 | Q61: 2400 | R61: 0 | S61: =SUM(M61:P61)+R61 -> 46 | T61: =IFERROR(S61/Q61,0) -> 0.019166667 | U61: =TEXT(B61,"dddd") -> Friday | V61: Feature feedback | W61: No | X61: text, referenced_tweets | Y61: =IF(AND(Q61>MEDIAN($Q$2:$Q$61), T61<MEDIAN($T$2:$T$61)),"Yes","No") -> No

Sheet Data_Dictionary
A1: Column | B1: Description | C1: Student use | D1: X/Twitter API or analytics concept
A2: post_id | B2: Unique identifier for each simulated social media item. | C2: Reference individual posts when discussing findings. | D2: id
A3: post_datetime | B3: Date and time the post was published. | C3: Analyze timing, trends, and day-of-week patterns. | D3: created_at
A4: post_type | B4: Whether the row is a brand post, customer reply, mention, or quote post. | C4: Compare original posts with customer interactions. | D4: referenced_tweets, conversation_id
A5: author_type | B5: Simplified category of the account that created the post. | C5: Explore who is engaging with the brand. | D5: author_id with user profile enrichment
A6: author_follower_bucket | B6: Approximate audience-size bucket for the author. | C6: Compare engagement from smaller vs. larger accounts. | D6: public_metrics.followers_count
A7: post_text | B7: Simulated text content of the social media post. | C7: Perform topic, keyword, and sentiment analysis. | D7: text
A8: topic | B8: Curated topic label for the post. | C8: Group posts into themes such as fraud, app issues, or financial wellbeing. | D8: Derived classification from text/entities
A9: content_format | B9: Simplified format of the post: text, image, video, link, etc. | C9: Compare engagement by format. | D9: attachments, media_keys, entities.urls
A10: hashtags | B10: Hashtags included in the simulated post. | C10: Identify recurring campaign or topic markers. | D10: entities.hashtags
A11: mentions_commbank | B11: Whether the post mentions Commonwealth Bank. | C11: Separate brand-originated posts from customer mentions. | D11: entities.mentions
A12: sentiment_label | B12: Curated sentiment category. | C12: Summarize positive, negative, neutral, and mixed responses. | D12: Derived NLP output
... A25: api_field_examples | B25: Examples of API fields or concepts that could produce similar information. | C25: Connect the dataset back to API documentation. | D25: Documentation mapping

Sheet Analysis_Prompts
A1: Analysis area | B1: Question learners can answer with the dataset | C1: Relevant columns
A2: Topic analysis | B2: Which topics appear most often, and what do those topics suggest customers care about? | C2: topic, post_text, hashtags
A3: Engagement analysis | B3: Which posts generate the most total engagement? Do the highest-view posts also receive the highest engagement? | C3: likes, replies, reposts, quote_posts, views, link_clicks, total_engagements, engagement_rate
A4: Sentiment analysis | B4: Which topics have the most positive, negative, neutral, or mixed sentiment? | C4: topic, sentiment_label, sentiment_score
A5: Customer support | B5: Which posts likely require a response from CommBank, and what themes do they share? | C5: post_type, customer_intent, response_needed, topic, post_text
A6: Trend analysis | B6: Do certain topics or sentiment patterns appear more often on specific dates or days of the week? | C6: post_datetime, day_of_week, topic, sentiment_label
A7: Marketing insight | B7: Which formats or campaign themes appear to resonate most with audiences? | C7: content_format, hashtags, topic, engagement_rate
A8: Product insight | B8: What app, NetBank, card, or service improvements are customers requesting? | C8: topic, customer_intent, post_text
A9: Risk insight | B9: What scam or security concerns are most visible in the data? | C9: topic, customer_intent, sentiment_label, post_text

Sheet Resources
A1: Resource | B1: Use in task | C1: URL
A2: X API documentation | B2: Understand available fields and API concepts that can map to this dataset. | C2: http://docs.x.com/overview
A3: X API Getting Started PDF | B3: Reference for introductory API concepts. | C3: https://cdn.theforage.com/vinternships/companyassets/2sNmYuurxgpFYawco/y2NzZJASdgERdYR4S/1675682056660/getting_started.pdf
A4: Social media sentiment analysis | B4: Background reading for classifying positive, negative, neutral, and mixed social media text. | C4: Add program-approved URL here

Sheet Analyst
A2: 1. Topic frequency & engagement
A3: Topic | B3: Post Count | C3: Total Engagements | D3: Total Views | E3: Weighted Engagement Rate | F3: Average Sentiment Score
A4: Fraud & scams | B4: =COUNTIF(SocialMediaPosts[topic],A4) -> 11 | C4: =SUMIF(SocialMediaPosts[topic],A4,SocialMediaPosts[total_engagements]) -> 36283 | D4: =SUMIF(SocialMediaPosts[topic],A4,SocialMediaPosts[views]) -> 680750 | E4: =C4/D4 -> 0.053298568 | F4: =AVERAGEIF(SocialMediaPosts[topic],A4,SocialMediaPosts[sentiment_score]) -> 0.21454545
A5: Financial wellbeing | B5: =COUNTIF(SocialMediaPosts[topic],A5) -> 9 | C5: =SUMIF(SocialMediaPosts[topic],A5,SocialMediaPosts[total_engagements]) -> 23309 | D5: =SUMIF(SocialMediaPosts[topic],A5,SocialMediaPosts[views]) -> 513500 | E5: =C5/D5 -> 0.045392405 | F5: =AVERAGEIF(SocialMediaPosts[topic],A5,SocialMediaPosts[sentiment_score]) -> 0.38777778
A6: Security education | B6: =COUNTIF(SocialMediaPosts[topic],A6) -> 5 | C6: =SUMIF(SocialMediaPosts[topic],A6,SocialMediaPosts[total_engagements]) -> 22360 | D6: =SUMIF(SocialMediaPosts[topic],A6,SocialMediaPosts[views]) -> 439800 | E6: =C6/D6 -> 0.050841291 | F6: =AVERAGEIF(SocialMediaPosts[topic],A6,SocialMediaPosts[sentiment_score]) -> 0.352
A7: Digital banking | B7: =COUNTIF(SocialMediaPosts[topic],A7) -> 13 | C7: =SUMIF(SocialMediaPosts[topic],A7,SocialMediaPosts[total_engagements]) -> 21176 | D7: =SUMIF(SocialMediaPosts[topic],A7,SocialMediaPosts[views]) -> 540300 | E7: =C7/D7 -> 0.039193041 | F7: =AVERAGEIF(SocialMediaPosts[topic],A7,SocialMediaPosts[sentiment_score]) -> 0.021538462
A8: Card services | B8: =COUNTIF(SocialMediaPosts[topic],A8) -> 4 | C8: =SUMIF(SocialMediaPosts[topic],A8,SocialMediaPosts[total_engagements]) -> 8303 | D8: =SUMIF(SocialMediaPosts[topic],A8,SocialMediaPosts[views]) -> 192450 | E8: =C8/D8 -> 0.043143674 | F8: =AVERAGEIF(SocialMediaPosts[topic],A8,SocialMediaPosts[sentiment_score]) -> 0.375
A9: Community | B9: =COUNTIF(SocialMediaPosts[topic],A9) -> 4 | C9: =SUMIF(SocialMediaPosts[topic],A9,SocialMediaPosts[total_engagements]) -> 8279 | D9: =SUMIF(SocialMediaPosts[topic],A9,SocialMediaPosts[views]) -> 238100 | E9: =C9/D9 -> 0.034771105 | F9: =AVERAGEIF(SocialMediaPosts[topic],A9,SocialMediaPosts[sentiment_score]) -> 0.765
A10: Business banking | B10: =COUNTIF(SocialMediaPosts[topic],A10) -> 3 | C10: =SUMIF(SocialMediaPosts[topic],A10,SocialMediaPosts[total_engagements]) -> 2671 | D10: =SUMIF(SocialMediaPosts[topic],A10,SocialMediaPosts[views]) -> 59900 | E10: =C10/D10 -> 0.044590985 | F10: =AVERAGEIF(SocialMediaPosts[topic],A10,SocialMediaPosts[sentiment_score]) -> 0.44666667
A11: Sustainability | B11: =COUNTIF(SocialMediaPosts[topic],A11) -> 2 | C11: =SUMIF(SocialMediaPosts[topic],A11,SocialMediaPosts[total_engagements]) -> 1787 | D11: =SUMIF(SocialMediaPosts[topic],A11,SocialMediaPosts[views]) -> 101400 | E11: =C11/D11 -> 0.017623274 | F11: =AVERAGEIF(SocialMediaPosts[topic],A11,SocialMediaPosts[sentiment_score]) -> 0.17
A12: Outage/service issue | B12: =COUNTIF(SocialMediaPosts[topic],A12) -> 5 | C12: =SUMIF(SocialMediaPosts[topic],A12,SocialMediaPosts[total_engagements]) -> 1714 | D12: =SUMIF(SocialMediaPosts[topic],A12,SocialMediaPosts[views]) -> 132140 | E12: =C12/D12 -> 0.012971091 | F12: =AVERAGEIF(SocialMediaPosts[topic],A12,SocialMediaPosts[sentiment_score]) -> -0.2
A13: Branch/ATM | B13: =COUNTIF(SocialMediaPosts[topic],A13) -> 3 | C13: =SUMIF(SocialMediaPosts[topic],A13,SocialMediaPosts[total_engagements]) -> 90 | D13: =SUMIF(SocialMediaPosts[topic],A13,SocialMediaPosts[views]) -> 5750 | E13: =C13/D13 -> 0.015652174 | F13: =AVERAGEIF(SocialMediaPosts[topic],A13,SocialMediaPosts[sentiment_score]) -> -0.63333333
A14: Customer support | B14: =COUNTIF(SocialMediaPosts[topic],A14) -> 1 | C14: =SUMIF(SocialMediaPosts[topic],A14,SocialMediaPosts[total_engagements]) -> 17 | D14: =SUMIF(SocialMediaPosts[topic],A14,SocialMediaPosts[views]) -> 2100 | E14: =C14/D14 -> 0.0080952381 | F14: =AVERAGEIF(SocialMediaPosts[topic],A14,SocialMediaPosts[sentiment_score]) -> 0.05
A15: Total | B15: =SUM(B4:B14) -> 60 | C15: =SUM(C4:C14) -> 125989 | D15: =SUM(D4:D14) -> 2906190 | E15: =C15/D15 -> 0.043351949 | F15: =AVERAGE(F4:F14) -> 0.17719955
A17: 2. Sentiment mix by topic
A18: Topic | B18: Positive | C18: Neutral | D18: Negative | E18: Mixed | F18: Total Post
A19: Fraud & scams | B19: =COUNTIFS(SocialMediaPosts[topic],Analyst!$A19,SocialMediaPosts[sentiment_label],Analyst!B$18) -> 5 | C19: =COUNTIFS(SocialMediaPosts[topic],Analyst!$A19,SocialMediaPosts[sentiment_label],Analyst!C$18) -> 3 | D19: =COUNTIFS(SocialMediaPosts[topic],Analyst!$A19,SocialMediaPosts[sentiment_label],Analyst!D$18) -> 2 | E19: =COUNTIFS(SocialMediaPosts[topic],Analyst!$A19,SocialMediaPosts[sentiment_label],Analyst!E$18) -> 1 | F19: =SUM(B19:E19) -> 11
A20: Financial wellbeing | B20: =COUNTIFS(SocialMediaPosts[topic],Analyst!$A20,SocialMediaPosts[sentiment_label],Analyst!B$18) -> 4 | C20: =COUNTIFS(SocialMediaPosts[topic],Analyst!$A20,SocialMediaPosts[sentiment_label],Analyst!C$18) -> 5 | D20: =COUNTIFS(SocialMediaPosts[topic],Analyst!$A20,SocialMediaPosts[sentiment_label],Analyst!D$18) -> 0 | E20: =COUNTIFS(SocialMediaPosts[topic],Analyst!$A20,SocialMediaPosts[sentiment_label],Analyst!E$18) -> 0 | F20: =SUM(B20:E20) -> 9
A21: Security education | B21: =COUNTIFS(SocialMediaPosts[topic],Analyst!$A21,SocialMediaPosts[sentiment_label],Analyst!B$18) -> 3 | C21: =COUNTIFS(SocialMediaPosts[topic],Analyst!$A21,SocialMediaPosts[sentiment_label],Analyst!C$18) -> 1 | D21: =COUNTIFS(SocialMediaPosts[topic],Analyst!$A21,SocialMediaPosts[sentiment_label],Analyst!D$18) -> 0 | E21: =COUNTIFS(SocialMediaPosts[topic],Analyst!$A21,SocialMediaPosts[sentiment_label],Analyst!E$18) -> 1 | F21: =SUM(B21:E21) -> 5
A22: Digital banking | B22: =COUNTIFS(SocialMediaPosts[topic],Analyst!$A22,SocialMediaPosts[sentiment_label],Analyst!B$18) -> 4 | C22: =COUNTIFS(SocialMediaPosts[topic],Analyst!$A22,SocialMediaPosts[sentiment_label],Analyst!C$18) -> 1 | D22: =COUNTIFS(SocialMediaPosts[topic],Analyst!$A22,SocialMediaPosts[sentiment_label],Analyst!D$18) -> 4 | E22: =COUNTIFS(SocialMediaPosts[topic],Analyst!$A22,SocialMediaPosts[sentiment_label],Analyst!E$18) -> 4 | F22: =SUM(B22:E22) -> 13
A23: Card services | B23: =COUNTIFS(SocialMediaPosts[topic],Analyst!$A23,SocialMediaPosts[sentiment_label],Analyst!B$18) -> 2 | C23: =COUNTIFS(SocialMediaPosts[topic],Analyst!$A23,SocialMediaPosts[sentiment_label],Analyst!C$18) -> 2 | D23: =COUNTIFS(SocialMediaPosts[topic],Analyst!$A23,SocialMediaPosts[sentiment_label],Analyst!D$18) -> 0 | E23: =COUNTIFS(SocialMediaPosts[topic],Analyst!$A23,SocialMediaPosts[sentiment_label],Analyst!E$18) -> 0 | F23: =SUM(B23:E23) -> 4
A24: Community | B24: =COUNTIFS(SocialMediaPosts[topic],Analyst!$A24,SocialMediaPosts[sentiment_label],Analyst!B$18) -> 4 | C24: =COUNTIFS(SocialMediaPosts[topic],Analyst!$A24,SocialMediaPosts[sentiment_label],Analyst!C$18) -> 0 | D24: =COUNTIFS(SocialMediaPosts[topic],Analyst!$A24,SocialMediaPosts[sentiment_label],Analyst!D$18) -> 0 | E24: =COUNTIFS(SocialMediaPosts[topic],Analyst!$A24,SocialMediaPosts[sentiment_label],Analyst!E$18) -> 0 | F24: =SUM(B24:E24) -> 4
A25: Business banking | B25: =COUNTIFS(SocialMediaPosts[topic],Analyst!$A25,SocialMediaPosts[sentiment_label],Analyst!B$18) -> 2 | C25: =COUNTIFS(SocialMediaPosts[topic],Analyst!$A25,SocialMediaPosts[sentiment_label],Analyst!C$18) -> 0 | D25: =COUNTIFS(SocialMediaPosts[topic],Analyst!$A25,SocialMediaPosts[sentiment_label],Analyst!D$18) -> 0 | E25: =COUNTIFS(SocialMediaPosts[topic],Analyst!$A25,SocialMediaPosts[sentiment_label],Analyst!E$18) -> 1 | F25: =SUM(B25:E25) -> 3
A26: Sustainability | B26: =COUNTIFS(SocialMediaPosts[topic],Analyst!$A26,SocialMediaPosts[sentiment_label],Analyst!B$18) -> 1 | C26: =COUNTIFS(SocialMediaPosts[topic],Analyst!$A26,SocialMediaPosts[sentiment_label],Analyst!C$18) -> 0 | D26: =COUNTIFS(SocialMediaPosts[topic],Analyst!$A26,SocialMediaPosts[sentiment_label],Analyst!D$18) -> 0 | E26: =COUNTIFS(SocialMediaPosts[topic],Analyst!$A26,SocialMediaPosts[sentiment_label],Analyst!E$18) -> 1 | F26: =SUM(B26:E26) -> 2
A27: Outage/service issue | B27: =COUNTIFS(SocialMediaPosts[topic],Analyst!$A27,SocialMediaPosts[sentiment_label],Analyst!B$18) -> 1 | C27: =COUNTIFS(SocialMediaPosts[topic],Analyst!$A27,SocialMediaPosts[sentiment_label],Analyst!C$18) -> 2 | D27: =COUNTIFS(SocialMediaPosts[topic],Analyst!$A27,SocialMediaPosts[sentiment_label],Analyst!D$18) -> 2 | E27: =COUNTIFS(SocialMediaPosts[topic],Analyst!$A27,SocialMediaPosts[sentiment_label],Analyst!E$18) -> 0 | F27: =SUM(B27:E27) -> 5
A28: Branch/ATM | B28: =COUNTIFS(SocialMediaPosts[topic],Analyst!$A28,SocialMediaPosts[sentiment_label],Analyst!B$18) -> 0 | C28: =COUNTIFS(SocialMediaPosts[topic],Analyst!$A28,SocialMediaPosts[sentiment_label],Analyst!C$18) -> 0 | D28: =COUNTIFS(SocialMediaPosts[topic],Analyst!$A28,SocialMediaPosts[sentiment_label],Analyst!D$18) -> 3 | E28: =COUNTIFS(SocialMediaPosts[topic],Analyst!$A28,SocialMediaPosts[sentiment_label],Analyst!E$18) -> 0 | F28: =SUM(B28:E28) -> 3
A29: Customer support | B29: =COUNTIFS(SocialMediaPosts[topic],Analyst!$A29,SocialMediaPosts[sentiment_label],Analyst!B$18) -> 0 | C29: =COUNTIFS(SocialMediaPosts[topic],Analyst!$A29,SocialMediaPosts[sentiment_label],Analyst!C$18) -> 1 | D29: =COUNTIFS(SocialMediaPosts[topic],Analyst!$A29,SocialMediaPosts[sentiment_label],Analyst!D$18) -> 0 | E29: =COUNTIFS(SocialMediaPosts[topic],Analyst!$A29,SocialMediaPosts[sentiment_label],Analyst!E$18) -> 0 | F29: =SUM(B29:E29) -> 1
A30: Total | B30: =SUM(B19:B29) -> 26 | C30: =SUM(C19:C29) -> 15 | D30: =SUM(D19:D29) -> 11 | E30: =SUM(E19:E29) -> 8 | F30: =SUM(F19:F29) -> 60
A32: 3. Response-needed posts by topic
A33: Topic | B33: Needed Response | C33: No Response Needed | D33: Total Posts | E33: % Needing Response
A34: Fraud & scams | B34: =COUNTIFS(SocialMediaPosts[topic],Analyst!$A34,SocialMediaPosts[response_needed],"Yes") -> 2 | C34: =COUNTIFS(SocialMediaPosts[topic],Analyst!$A34,SocialMediaPosts[response_needed],"No") -> 9 | D34: =SUM(B34:C34) -> 11 | E34: =B34/D34 -> 0.18181818
A35: Financial wellbeing | B35: =COUNTIFS(SocialMediaPosts[topic],Analyst!$A35,SocialMediaPosts[response_needed],"Yes") -> 0 | C35: =COUNTIFS(SocialMediaPosts[topic],Analyst!$A35,SocialMediaPosts[response_needed],"No") -> 9 | D35: =SUM(B35:C35) -> 9 | E35: =B35/D35 -> 0
A36: Security education | B36: =COUNTIFS(SocialMediaPosts[topic],Analyst!$A36,SocialMediaPosts[response_needed],"Yes") -> 0 | C36: =COUNTIFS(SocialMediaPosts[topic],Analyst!$A36,SocialMediaPosts[response_needed],"No") -> 5 | D36: =SUM(B36:C36) -> 5 | E36: =B36/D36 -> 0
A37: Digital banking | B37: =COUNTIFS(SocialMediaPosts[topic],Analyst!$A37,SocialMediaPosts[response_needed],"Yes") -> 3 | C37: =COUNTIFS(SocialMediaPosts[topic],Analyst!$A37,SocialMediaPosts[response_needed],"No") -> 10 | D37: =SUM(B37:C37) -> 13 | E37: =B37/D37 -> 0.23076923
A38: Card services | B38: =COUNTIFS(SocialMediaPosts[topic],Analyst!$A38,SocialMediaPosts[response_needed],"Yes") -> 1 | C38: =COUNTIFS(SocialMediaPosts[topic],Analyst!$A38,SocialMediaPosts[response_needed],"No") -> 3 | D38: =SUM(B38:C38) -> 4 | E38: =B38/D38 -> 0.25
A39: Community | B39: =COUNTIFS(SocialMediaPosts[topic],Analyst!$A39,SocialMediaPosts[response_needed],"Yes") -> 0 | C39: =COUNTIFS(SocialMediaPosts[topic],Analyst!$A39,SocialMediaPosts[response_needed],"No") -> 4 | D39: =SUM(B39:C39) -> 4 | E39: =B39/D39 -> 0
A40: Business banking | B40: =COUNTIFS(SocialMediaPosts[topic],Analyst!$A40,SocialMediaPosts[response_needed],"Yes") -> 0 | C40: =COUNTIFS(SocialMediaPosts[topic],Analyst!$A40,SocialMediaPosts[response_needed],"No") -> 3 | D40: =SUM(B40:C40) -> 3 | E40: =B40/D40 -> 0
A41: Sustainability | B41: =COUNTIFS(SocialMediaPosts[topic],Analyst!$A41,SocialMediaPosts[response_needed],"Yes") -> 0 | C41: =COUNTIFS(SocialMediaPosts[topic],Analyst!$A41,SocialMediaPosts[response_needed],"No") -> 2 | D41: =SUM(B41:C41) -> 2 | E41: =B41/D41 -> 0
A42: Outage/service issue | B42: =COUNTIFS(SocialMediaPosts[topic],Analyst!$A42,SocialMediaPosts[response_needed],"Yes") -> 2 | C42: =COUNTIFS(SocialMediaPosts[topic],Analyst!$A42,SocialMediaPosts[response_needed],"No") -> 3 | D42: =SUM(B42:C42) -> 5 | E42: =B42/D42 -> 0.4
A43: Branch/ATM | B43: =COUNTIFS(SocialMediaPosts[topic],Analyst!$A43,SocialMediaPosts[response_needed],"Yes") -> 3 | C43: =COUNTIFS(SocialMediaPosts[topic],Analyst!$A43,SocialMediaPosts[response_needed],"No") -> 0 | D43: =SUM(B43:C43) -> 3 | E43: =B43/D43 -> 1
A44: Customer support | B44: =COUNTIFS(SocialMediaPosts[topic],Analyst!$A44,SocialMediaPosts[response_needed],"Yes") -> 0 | C44: =COUNTIFS(SocialMediaPosts[topic],Analyst!$A44,SocialMediaPosts[response_needed],"No") -> 1 | D44: =SUM(B44:C44) -> 1 | E44: =B44/D44 -> 0
A45: Total | B45: =SUM(B34:B44) -> 11 | C45: =SUM(C34:C44) -> 49 | D45: =SUM(D34:D44) -> 60 | E45: =B45/D45 -> 0.18333333
A47: 4. Day of week summary
A48: Day | B48: Post Count | C48: Total Engagements | D48: Average Sentiment Score
A49: Monday | B49: =COUNTIF(SocialMediaPosts[day_of_week],Analyst!A49) -> 6 | C49: =SUMIF(SocialMediaPosts[day_of_week],Analyst!A49,SocialMediaPosts[total_engagements]) -> 7905 | D49: =AVERAGEIF(SocialMediaPosts[day_of_week],Analyst!A49,SocialMediaPosts[sentiment_score]) -> 0.053333333
A50: Tuesday | B50: =COUNTIF(SocialMediaPosts[day_of_week],Analyst!A50) -> 11 | C50: =SUMIF(SocialMediaPosts[day_of_week],Analyst!A50,SocialMediaPosts[total_engagements]) -> 32955 | D50: =AVERAGEIF(SocialMediaPosts[day_of_week],Analyst!A50,SocialMediaPosts[sentiment_score]) -> 0.21454545
A51: Wednesday | B51: =COUNTIF(SocialMediaPosts[day_of_week],Analyst!A51) -> 11 | C51: =SUMIF(SocialMediaPosts[day_of_week],Analyst!A51,SocialMediaPosts[total_engagements]) -> 25565 | D51: =AVERAGEIF(SocialMediaPosts[day_of_week],Analyst!A51,SocialMediaPosts[sentiment_score]) -> 0.068181818
A52: Thursday | B52: =COUNTIF(SocialMediaPosts[day_of_week],Analyst!A52) -> 10 | C52: =SUMIF(SocialMediaPosts[day_of_week],Analyst!A52,SocialMediaPosts[total_engagements]) -> 15892 | D52: =AVERAGEIF(SocialMediaPosts[day_of_week],Analyst!A52,SocialMediaPosts[sentiment_score]) -> 0.325
A53: Friday | B53: =COUNTIF(SocialMediaPosts[day_of_week],Analyst!A53) -> 8 | C53: =SUMIF(SocialMediaPosts[day_of_week],Analyst!A53,SocialMediaPosts[total_engagements]) -> 15011 | D53: =AVERAGEIF(SocialMediaPosts[day_of_week],Analyst!A53,SocialMediaPosts[sentiment_score]) -> 0.0875
A54: Saturday | B54: =COUNTIF(SocialMediaPosts[day_of_week],Analyst!A54) -> 7 | C54: =SUMIF(SocialMediaPosts[day_of_week],Analyst!A54,SocialMediaPosts[total_engagements]) -> 5999 | D54: =AVERAGEIF(SocialMediaPosts[day_of_week],Analyst!A54,SocialMediaPosts[sentiment_score]) -> 0.13857143
A55: Sunday | B55: =COUNTIF(SocialMediaPosts[day_of_week],Analyst!A55) -> 7 | C55: =SUMIF(SocialMediaPosts[day_of_week],Analyst!A55,SocialMediaPosts[total_engagements]) -> 22662 | D55: =AVERAGEIF(SocialMediaPosts[day_of_week],Analyst!A55,SocialMediaPosts[sentiment_score]) -> 0.41857143
A56: Total | B56: =SUM(B49:B55) -> 60 | C56: =SUM(C49:C55) -> 125989 | D56: =AVERAGE(D49:D55) -> 0.18652907
A58: 5. Sentiment mix by day of week
A59: Day | B59: Positive | C59: Neutral | D59: Negative | E59: Mixed | F59: Total Post
A60: Monday | B60: =COUNTIFS(SocialMediaPosts[day_of_week],Analyst!$A60,SocialMediaPosts[sentiment_label],Analyst!B$59) -> 1 | C60: =COUNTIFS(SocialMediaPosts[day_of_week],Analyst!$A60,SocialMediaPosts[sentiment_label],Analyst!C$59) -> 3 | D60: =COUNTIFS(SocialMediaPosts[day_of_week],Analyst!$A60,SocialMediaPosts[sentiment_label],Analyst!D$59) -> 1 | E60: =COUNTIFS(SocialMediaPosts[day_of_week],Analyst!$A60,SocialMediaPosts[sentiment_label],Analyst!E$59) -> 1 | F60: =SUM(B60:E60) -> 6
A61: Tuesday | B61: =COUNTIFS(SocialMediaPosts[day_of_week],Analyst!$A61,SocialMediaPosts[sentiment_label],Analyst!B$59) -> 6 | C61: =COUNTIFS(SocialMediaPosts[day_of_week],Analyst!$A61,SocialMediaPosts[sentiment_label],Analyst!C$59) -> 1 | D61: =COUNTIFS(SocialMediaPosts[day_of_week],Analyst!$A61,SocialMediaPosts[sentiment_label],Analyst!D$59) -> 2 | E61: =COUNTIFS(SocialMediaPosts[day_of_week],Analyst!$A61,SocialMediaPosts[sentiment_label],Analyst!E$59) -> 2 | F61: =SUM(B61:E61) -> 11
A62: Wednesday | B62: =COUNTIFS(SocialMediaPosts[day_of_week],Analyst!$A62,SocialMediaPosts[sentiment_label],Analyst!B$59) -> 5 | C62: =COUNTIFS(SocialMediaPosts[day_of_week],Analyst!$A62,SocialMediaPosts[sentiment_label],Analyst!C$59) -> 1 | D62: =COUNTIFS(SocialMediaPosts[day_of_week],Analyst!$A62,SocialMediaPosts[sentiment_label],Analyst!D$59) -> 4 | E62: =COUNTIFS(SocialMediaPosts[day_of_week],Analyst!$A62,SocialMediaPosts[sentiment_label],Analyst!E$59) -> 1 | F62: =SUM(B62:E62) -> 11
A63: Thursday | B63: =COUNTIFS(SocialMediaPosts[day_of_week],Analyst!$A63,SocialMediaPosts[sentiment_label],Analyst!B$59) -> 6 | C63: =COUNTIFS(SocialMediaPosts[day_of_week],Analyst!$A63,SocialMediaPosts[sentiment_label],Analyst!C$59) -> 2 | D63: =COUNTIFS(SocialMediaPosts[day_of_week],Analyst!$A63,SocialMediaPosts[sentiment_label],Analyst!D$59) -> 1 | E63: =COUNTIFS(SocialMediaPosts[day_of_week],Analyst!$A63,SocialMediaPosts[sentiment_label],Analyst!E$59) -> 1 | F63: =SUM(B63:E63) -> 10
A64: Friday | B64: =COUNTIFS(SocialMediaPosts[day_of_week],Analyst!$A64,SocialMediaPosts[sentiment_label],Analyst!B$59) -> 3 | C64: =COUNTIFS(SocialMediaPosts[day_of_week],Analyst!$A64,SocialMediaPosts[sentiment_label],Analyst!C$59) -> 2 | D64: =COUNTIFS(SocialMediaPosts[day_of_week],Analyst!$A64,SocialMediaPosts[sentiment_label],Analyst!D$59) -> 2 | E64: =COUNTIFS(SocialMediaPosts[day_of_week],Analyst!$A64,SocialMediaPosts[sentiment_label],Analyst!E$59) -> 1 | F64: =SUM(B64:E64) -> 8
A65: Saturday | B65: =COUNTIFS(SocialMediaPosts[day_of_week],Analyst!$A65,SocialMediaPosts[sentiment_label],Analyst!B$59) -> 1 | C65: =COUNTIFS(SocialMediaPosts[day_of_week],Analyst!$A65,SocialMediaPosts[sentiment_label],Analyst!C$59) -> 4 | D65: =COUNTIFS(SocialMediaPosts[day_of_week],Analyst!$A65,SocialMediaPosts[sentiment_label],Analyst!D$59) -> 1 | E65: =COUNTIFS(SocialMediaPosts[day_of_week],Analyst!$A65,SocialMediaPosts[sentiment_label],Analyst!E$59) -> 1 | F65: =SUM(B65:E65) -> 7
A66: Sunday | B66: =COUNTIFS(SocialMediaPosts[day_of_week],Analyst!$A66,SocialMediaPosts[sentiment_label],Analyst!B$59) -> 4 | C66: =COUNTIFS(SocialMediaPosts[day_of_week],Analyst!$A66,SocialMediaPosts[sentiment_label],Analyst!C$59) -> 2 | D66: =COUNTIFS(SocialMediaPosts[day_of_week],Analyst!$A66,SocialMediaPosts[sentiment_label],Analyst!D$59) -> 0 | E66: =COUNTIFS(SocialMediaPosts[day_of_week],Analyst!$A66,SocialMediaPosts[sentiment_label],Analyst!E$59) -> 1 | F66: =SUM(B66:E66) -> 7
A67: Total | B67: =SUM(B60:B66) -> 26 | C67: =SUM(C60:C66) -> 15 | D67: =SUM(D60:D66) -> 11 | E67: =SUM(E60:E66) -> 8 | F67: =SUM(F60:F66) -> 60
A69: 6. Content format resonance
A70: Content Format | B70: Post Count | C70: Total Engagements | D70: Total Views | E70: Weighted Engagement Rate
A71: Text | B71: =COUNTIF(SocialMediaPosts[content_format],Analyst!A71) -> 36 | C71: =SUMIF(SocialMediaPosts[content_format],Analyst!A71,SocialMediaPosts[total_engagements]) -> 3809 | D71: =SUMIF(SocialMediaPosts[content_format],Analyst!A71,SocialMediaPosts[views]) -> 264990 | E71: =C71/D71 -> 0.014374127
A72: Text + image | B72: =COUNTIF(SocialMediaPosts[content_format],Analyst!A72) -> 14 | C72: =SUMIF(SocialMediaPosts[content_format],Analyst!A72,SocialMediaPosts[total_engagements]) -> 73358 | D72: =SUMIF(SocialMediaPosts[content_format],Analyst!A72,SocialMediaPosts[views]) -> 1590300 | E72: =C72/D72 -> 0.046128403
A73: Text + video | B73: =COUNTIF(SocialMediaPosts[content_format],Analyst!A73) -> 4 | C73: =SUMIF(SocialMediaPosts[content_format],Analyst!A73,SocialMediaPosts[total_engagements]) -> 27084 | D73: =SUMIF(SocialMediaPosts[content_format],Analyst!A73,SocialMediaPosts[views]) -> 524000 | E73: =C73/D73 -> 0.051687023
A74: Link | B74: =COUNTIF(SocialMediaPosts[content_format],Analyst!A74) -> 6 | C74: =SUMIF(SocialMediaPosts[content_format],Analyst!A74,SocialMediaPosts[total_engagements]) -> 21738 | D74: =SUMIF(SocialMediaPosts[content_format],Analyst!A74,SocialMediaPosts[views]) -> 526900 | E74: =C74/D74 -> 0.041256405
A75: Total | B75: =SUM(B71:B74) -> 60 | C75: =SUM(C71:C74) -> 125989 | D75: =SUM(D71:D74) -> 2906190 | E75: =C75/D75 -> 0.043351949
A77: 7. High-views / low engagement posts by topis
A78: Topic | B78: Needed Response | C78: Total Posts | D78: % Needing Response
A79: Fraud & scams | B79: =COUNTIFS(SocialMediaPosts[topic],Analyst!$A79,SocialMediaPosts[high_views_low_engage],"Yes") -> 2 | C79: =COUNTIF(SocialMediaPosts[topic],Analyst!A79) -> 11 | D79: =IF(C79=0,0,B79/C79) -> 0.18181818
A80: Financial wellbeing | B80: =COUNTIFS(SocialMediaPosts[topic],Analyst!$A80,SocialMediaPosts[high_views_low_engage],"Yes") -> 1 | C80: =COUNTIF(SocialMediaPosts[topic],Analyst!A80) -> 9 | D80: =IF(C80=0,0,B80/C80) -> 0.11111111
A81: Security education | B81: =COUNTIFS(SocialMediaPosts[topic],Analyst!$A81,SocialMediaPosts[high_views_low_engage],"Yes") -> 0 | C81: =COUNTIF(SocialMediaPosts[topic],Analyst!A81) -> 5 | D81: =IF(C81=0,0,B81/C81) -> 0
A82: Digital banking | B82: =COUNTIFS(SocialMediaPosts[topic],Analyst!$A82,SocialMediaPosts[high_views_low_engage],"Yes") -> 1 | C82: =COUNTIF(SocialMediaPosts[topic],Analyst!A82) -> 13 | D82: =IF(C82=0,0,B82/C82) -> 0.076923077
A83: Card services | B83: =COUNTIFS(SocialMediaPosts[topic],Analyst!$A83,SocialMediaPosts[high_views_low_engage],"Yes") -> 0 | C83: =COUNTIF(SocialMediaPosts[topic],Analyst!A83) -> 4 | D83: =IF(C83=0,0,B83/C83) -> 0
A84: Community | B84: =COUNTIFS(SocialMediaPosts[topic],Analyst!$A84,SocialMediaPosts[high_views_low_engage],"Yes") -> 0 | C84: =COUNTIF(SocialMediaPosts[topic],Analyst!A84) -> 4 | D84: =IF(C84=0,0,B84/C84) -> 0
A85: Business banking | B85: =COUNTIFS(SocialMediaPosts[topic],Analyst!$A85,SocialMediaPosts[high_views_low_engage],"Yes") -> 0 | C85: =COUNTIF(SocialMediaPosts[topic],Analyst!A85) -> 3 | D85: =IF(C85=0,0,B85/C85) -> 0
A86: Sustainability | B86: =COUNTIFS(SocialMediaPosts[topic],Analyst!$A86,SocialMediaPosts[high_views_low_engage],"Yes") -> 1 | C86: =COUNTIF(SocialMediaPosts[topic],Analyst!A86) -> 2 | D86: =IF(C86=0,0,B86/C86) -> 0.5
A87: Outage/service issue | B87: =COUNTIFS(SocialMediaPosts[topic],Analyst!$A87,SocialMediaPosts[high_views_low_engage],"Yes") -> 3 | C87: =COUNTIF(SocialMediaPosts[topic],Analyst!A87) -> 5 | D87: =IF(C87=0,0,B87/C87) -> 0.6
A88: Branch/ATM | B88: =COUNTIFS(SocialMediaPosts[topic],Analyst!$A88,SocialMediaPosts[high_views_low_engage],"Yes") -> 0 | C88: =COUNTIF(SocialMediaPosts[topic],Analyst!A88) -> 3 | D88: =IF(C88=0,0,B88/C88) -> 0
A89: Customer support | B89: =COUNTIFS(SocialMediaPosts[topic],Analyst!$A89,SocialMediaPosts[high_views_low_engage],"Yes") -> 0 | C89: =COUNTIF(SocialMediaPosts[topic],Analyst!A89) -> 1 | D89: =IF(C89=0,0,B89/C89) -> 0
A90: Total | B90: =SUM(B79:B89) -> 8 | C90: =SUM(C79:C89) -> 60 | D90: =B90/C90 -> 0.13333333

Sheet Chart
